README.md
setup.py
jean_flores/__init__.py
jean_flores/cal.py
jean_flores.egg-info/PKG-INFO
jean_flores.egg-info/SOURCES.txt
jean_flores.egg-info/dependency_links.txt
jean_flores.egg-info/top_level.txt