Metadata-Version: 2.1
Name: jean_flores
Version: 0.0.1
Summary: Trabajo de modulos
Author: CARLO_10
Author-email: antonicontrerasaveiro@gmail.com
License: MIT
